rapidjson.cp314-win_amd64.pyd
python_rapidjson-1.23.dist-info/licenses/LICENSE
rapidjson-stubs/__init__.pyi
python_rapidjson-1.23.dist-info/METADATA
python_rapidjson-1.23.dist-info/WHEEL
python_rapidjson-1.23.dist-info/top_level.txt
python_rapidjson-1.23.dist-info/RECORD
